tenmactl/__init__.py
tenmactl-0.1.0.dist-info/DESCRIPTION.rst
tenmactl-0.1.0.dist-info/METADATA
tenmactl-0.1.0.dist-info/RECORD
tenmactl-0.1.0.dist-info/WHEEL
tenmactl-0.1.0.dist-info/metadata.json
tenmactl-0.1.0.dist-info/top_level.txt
